[
  {
    "name": {
      "list": [
        "Las Vegas Strip Circuit"
      ]
    },
    "url": "https://en.wikipedia.org/wiki/Las_Vegas_Strip_Circuit",
    "circuit_status": "current",
    "type": "Street circuit",
    "direction": "Anti-clockwise",
    "grands_prix": [
      {
        "text": "Las Vegas Grand Prix",
        "url": "https://en.wikipedia.org/wiki/Las_Vegas_Grand_Prix"
      }
    ],
    "seasons": [
      {
        "year": 2023,
        "url": "https://en.wikipedia.org/wiki/2023_Formula_One_World_Championship"
      },
      {
        "year": 2024,
        "url": "https://en.wikipedia.org/wiki/2024_Formula_One_World_Championship"
      },
      {
        "year": 2025,
        "url": "https://en.wikipedia.org/wiki/2025_Formula_One_World_Championship"
      }
    ],
    "grands_prix_held": 3,
    "location": {
      "places": [
        {
          "text": "Paradise",
          "url": "https://en.wikipedia.org/wiki/Paradise,_Nevada"
        },
        {
          "text": "Paradise, Nevada",
          "url": "https://en.wikipedia.org/wiki/Paradise,_Nevada"
        },
        {
          "text": "United States",
          "url": "https://en.wikipedia.org/wiki/United_States"
        }
      ],
      "coordinates": {
        "lat": 36.10995,
        "lon": -115.16217
      }
    },
    "fia_grade": 1,
    "history": [
      {
        "event": "broke_ground",
        "date": "2022-03"
      },
      {
        "event": "opened",
        "date": "2023-11-16"
      }
    ],
    "layouts": [
      {
        "layout": "Grand Prix Circuit",
        "years": "2023–present",
        "length_km": 6.201,
        "length_mi": 3.853,
        "turns": 17,
        "surface": {
          "values": [
            "Asphalt"
          ],
          "text": "Asphalt"
        },
        "race_lap_records": [
          {
            "event": {
              "text": "2025 Las Vegas Grand Prix",
              "url": "https://en.wikipedia.org/wiki/2025_Las_Vegas_Grand_Prix"
            },
            "driver": {
              "text": "Max Verstappen",
              "url": "https://en.wikipedia.org/wiki/Max_Verstappen"
            },
            "vehicle": {
              "text": "Red Bull Racing RB21",
              "url": "https://en.wikipedia.org/wiki/Red_Bull_Racing_RB21"
            },
            "time": 93.365,
            "year": "2025",
            "series": {
              "text": "Formula One",
              "url": "https://en.wikipedia.org/wiki/Formula_One"
            }
          },
          {
            "event": {
              "text": "2024 Las Vegas Ferrari Challenge North America round",
              "url": "https://en.wikipedia.org/wiki/Ferrari_Challenge#Ferrari_Challenge_North_America"
            },
            "driver": {
              "text": "Michael Verhagen"
            },
            "vehicle": {
              "text": "Ferrari 296 Challenge",
              "url": "https://en.wikipedia.org/wiki/Ferrari_296#296_Challenge"
            },
            "time": 114.677,
            "year": "2024",
            "series": {
              "text": "Ferrari Challenge",
              "url": "https://en.wikipedia.org/wiki/Ferrari_Challenge"
            }
          },
          {
            "event": {
              "text": "2025 Las Vegas F1 Academy round",
              "url": "https://en.wikipedia.org/wiki/2025_F1_Academy_season"
            },
            "driver": {
              "text": "Chloe Chambers",
              "url": "https://en.wikipedia.org/wiki/Chloe_Chambers"
            },
            "vehicle": {
              "text": "Tatuus F4-T421",
              "url": "https://en.wikipedia.org/wiki/Tatuus_F4-T421"
            },
            "time": 126.623,
            "year": "2025",
            "series": {
              "text": "Formula 4",
              "url": "https://en.wikipedia.org/wiki/Formula_4"
            }
          }
        ]
      }
    ]
  },
  {
    "name": {
      "list": [
        "Long Beach Street Circuit"
      ]
    },
    "circuit_status": "former",
    "type": "Street circuit",
    "direction": "Clockwise",
    "grands_prix": [
      {
        "text": "United States Grand Prix West",
        "url": "https://en.wikipedia.org/wiki/United_States_Grand_Prix_West"
      }
    ],
    "seasons": [
      {
        "year": 1976,
        "url": "https://en.wikipedia.org/wiki/1976_Formula_One_World_Championship"
      },
      {
        "year": 1977,
        "url": "https://en.wikipedia.org/wiki/1977_Formula_One_World_Championship"
      },
      {
        "year": 1978,
        "url": "https://en.wikipedia.org/wiki/1978_Formula_One_World_Championship"
      },
      {
        "year": 1979,
        "url": "https://en.wikipedia.org/wiki/1979_Formula_One_World_Championship"
      },
      {
        "year": 1980,
        "url": "https://en.wikipedia.org/wiki/1980_Formula_One_World_Championship"
      },
      {
        "year": 1981,
        "url": "https://en.wikipedia.org/wiki/1981_Formula_One_World_Championship"
      },
      {
        "year": 1982,
        "url": "https://en.wikipedia.org/wiki/1982_Formula_One_World_Championship"
      },
      {
        "year": 1983,
        "url": "https://en.wikipedia.org/wiki/1983_Formula_One_World_Championship"
      }
    ],
    "grands_prix_held": 8,
    "location": {
      "places": [
        {
          "text": "Long Beach",
          "url": "https://en.wikipedia.org/wiki/Long_Beach,_California"
        },
        {
          "text": "United States",
          "url": "https://en.wikipedia.org/wiki/United_States"
        }
      ],
      "coordinates": null
    }
  },
  {
    "name": {
      "list": [
        "Lusail International Circuit"
      ]
    },
    "url": "https://en.wikipedia.org/wiki/Lusail_International_Circuit",
    "circuit_status": "current",
    "type": "Race circuit",
    "direction": "Clockwise",
    "grands_prix": [
      {
        "text": "Qatar Grand Prix",
        "url": "https://en.wikipedia.org/wiki/Qatar_Grand_Prix"
      }
    ],
    "seasons": [
      {
        "year": 2021,
        "url": "https://en.wikipedia.org/wiki/2021_Formula_One_World_Championship"
      },
      {
        "year": 2023,
        "url": "https://en.wikipedia.org/wiki/2023_Formula_One_World_Championship"
      },
      {
        "year": 2024,
        "url": "https://en.wikipedia.org/wiki/2024_Formula_One_World_Championship"
      },
      {
        "year": 2025,
        "url": "https://en.wikipedia.org/wiki/2025_Formula_One_World_Championship"
      }
    ],
    "grands_prix_held": 4,
    "location": {
      "places": [
        {
          "text": "Lusail",
          "url": "https://en.wikipedia.org/wiki/Lusail"
        },
        {
          "text": "Al Daayen",
          "url": "https://en.wikipedia.org/wiki/Al_Daayen"
        },
        {
          "text": "Qatar",
          "url": "https://en.wikipedia.org/wiki/Qatar"
        }
      ],
      "coordinates": {
        "lat": 25.49,
        "lon": 51.45417
      }
    },
    "fia_grade": 1,
    "history": [
      {
        "event": "broke_ground",
        "date": "2003"
      },
      {
        "event": "opened",
        "date": "2004-09-30"
      }
    ],
    "layouts": [
      {
        "layout": "Grand Prix Circuit",
        "years": "2023–present",
        "length_km": 5.419,
        "length_mi": 3.367,
        "turns": 16,
        "race_lap_records": [
          {
            "event": {
              "text": "2024 Qatar Grand Prix",
              "url": "https://en.wikipedia.org/wiki/2024_Qatar_Grand_Prix"
            },
            "driver": {
              "text": "Lando Norris",
              "url": "https://en.wikipedia.org/wiki/Lando_Norris"
            },
            "vehicle": {
              "text": "McLaren MCL38",
              "url": "https://en.wikipedia.org/wiki/McLaren_MCL38"
            },
            "time": 82.384,
            "year": "2024",
            "series": {
              "text": "Formula One",
              "url": "https://en.wikipedia.org/wiki/Formula_One"
            }
          },
          {
            "event": {
              "text": "2024 Lusail Formula 2 round",
              "url": "https://en.wikipedia.org/wiki/2024_Lusail_Formula_2_round"
            },
            "driver": {
              "text": "Oliver Bearman",
              "url": "https://en.wikipedia.org/wiki/Oliver_Bearman"
            },
            "vehicle": {
              "text": "Dallara F2 2024",
              "url": "https://en.wikipedia.org/wiki/Dallara_F2_2024"
            },
            "time": 97.997,
            "year": "2024",
            "series": {
              "text": "FIA F2",
              "url": "https://en.wikipedia.org/wiki/FIA_Formula_2_Championship"
            }
          },
          {
            "event": {
              "text": "2024 Qatar 1812 km",
              "url": "https://en.wikipedia.org/wiki/2024_Qatar_1812_km"
            },
            "driver": {
              "text": "Matt Campbell",
              "url": "https://en.wikipedia.org/wiki/Matt_Campbell_(racing_driver)"
            },
            "vehicle": {
              "text": "Porsche 963",
              "url": "https://en.wikipedia.org/wiki/Porsche_963"
            },
            "time": 99.748,
            "year": "2024",
            "series": {
              "text": "LMDh",
              "url": "https://en.wikipedia.org/wiki/LMDh"
            }
          },
          {
            "event": {
              "text": "2025 Qatar 1812 km",
              "url": "https://en.wikipedia.org/wiki/2025_Qatar_1812_km"
            },
            "driver": {
              "text": "Alessandro Pier Guidi",
              "url": "https://en.wikipedia.org/wiki/Alessandro_Pier_Guidi"
            },
            "vehicle": {
              "text": "Ferrari 499P",
              "url": "https://en.wikipedia.org/wiki/Ferrari_499P"
            },
            "time": 101.259,
            "year": "2025",
            "series": {
              "text": "LMH",
              "url": "https://en.wikipedia.org/wiki/Le_Mans_Hypercar"
            }
          },
          {
            "event": {
              "text": "2026 Lusail Formula Regional Middle East round",
              "url": "https://en.wikipedia.org/wiki/2026_Formula_Regional_Middle_East_Trophy"
            },
            "driver": {
              "text": "Emanuele Olivieri",
              "url": "https://en.wikipedia.org/wiki/Emanuele_Olivieri"
            },
            "vehicle": {
              "text": "Tatuus T-326",
              "url": "https://en.wikipedia.org/wiki/Tatuus#Racecars"
            },
            "time": 108.18,
            "year": "2026",
            "series": {
              "text": "Formula Regional",
              "url": "https://en.wikipedia.org/wiki/Formula_Regional"
            }
          },
          {
            "event": {
              "text": "2025 Qatar motorcycle Grand Prix",
              "url": "https://en.wikipedia.org/wiki/2025_Qatar_motorcycle_Grand_Prix"
            },
            "driver": {
              "text": "Marc Márquez",
              "url": "https://en.wikipedia.org/wiki/Marc_M%C3%A1rquez"
            },
            "vehicle": {
              "text": "Ducati Desmosedici GP25",
              "url": "https://en.wikipedia.org/wiki/Ducati_Desmosedici"
            },
            "time": 112.561,
            "year": "2025",
            "series": {
              "text": "MotoGP",
              "url": "https://en.wikipedia.org/wiki/Grand_Prix_motorcycle_racing#MotoGP_class"
            }
          },
          {
            "event": {
              "text": "2024 Qatar 1812 km",
              "url": "https://en.wikipedia.org/wiki/2024_Qatar_1812_km"
            },
            "driver": {
              "text": "Alessio Rovera",
              "url": "https://en.wikipedia.org/wiki/Alessio_Rovera"
            },
            "vehicle": {
              "text": "Ferrari 296 GT3",
              "url": "https://en.wikipedia.org/wiki/Ferrari_296#296_GT3"
            },
            "time": 113.529,
            "year": "2024",
            "series": {
              "text": "GT3",
              "url": "https://en.wikipedia.org/wiki/Group_GT3"
            }
          },
          {
            "event": {
              "text": "2024 Lusail F1 Academy round",
              "url": "https://en.wikipedia.org/wiki/2024_F1_Academy_season"
            },
            "driver": {
              "text": "Doriane Pin",
              "url": "https://en.wikipedia.org/wiki/Doriane_Pin"
            },
            "vehicle": {
              "text": "Tatuus F4-T421",
              "url": "https://en.wikipedia.org/wiki/Tatuus_F4-T421"
            },
            "time": 114.996,
            "year": "2024",
            "series": {
              "text": "Formula 4",
              "url": "https://en.wikipedia.org/wiki/Formula_4"
            }
          },
          {
            "event": {
              "text": "2026 Ferrari Challenge Middle East Prologue"
            },
            "driver": {
              "text": "Fouad Alghanim"
            },
            "vehicle": {
              "text": "Ferrari 296 Challenge",
              "url": "https://en.wikipedia.org/wiki/Ferrari_296#296_Challenge"
            },
            "time": 116.741,
            "year": "2026",
            "series": {
              "text": "Ferrari Challenge",
              "url": "https://en.wikipedia.org/wiki/Ferrari_Challenge"
            }
          },
          {
            "event": {
              "text": "2023 Qatar motorcycle Grand Prix",
              "url": "https://en.wikipedia.org/wiki/2023_Qatar_motorcycle_Grand_Prix"
            },
            "driver": {
              "text": "Sam Lowes",
              "url": "https://en.wikipedia.org/wiki/Sam_Lowes"
            },
            "vehicle": {
              "text": "Kalex Moto2",
              "url": "https://en.wikipedia.org/wiki/Kalex"
            },
            "time": 117.366,
            "year": "2023",
            "series": {
              "text": "Moto2",
              "url": "https://en.wikipedia.org/wiki/Grand_Prix_motorcycle_racing#Moto2_class"
            }
          },
          {
            "event": {
              "text": "2025 Lusail Porsche Carrera Cup Middle East round",
              "url": "https://en.wikipedia.org/wiki/2025%E2%80%9326_Porsche_Carrera_Cup_Middle_East"
            },
            "driver": {
              "text": "Caleb Sumich"
            },
            "vehicle": {
              "text": "Porsche 911 (992) GT3 Cup",
              "url": "https://en.wikipedia.org/wiki/Porsche_911_GT3#992_GT3_Cup_(2021–)"
            },
            "time": 118.024,
            "year": "2025",
            "series": {
              "text": "Porsche Carrera Cup",
              "url": "https://en.wikipedia.org/wiki/Porsche_Carrera_Cup"
            }
          },
          {
            "event": {
              "text": "2025 1st Lusail QSTK 600 round"
            },
            "driver": {
              "text": "David Munoz Rodriguez"
            },
            "vehicle": {
              "text": "Yamaha YZF-R6",
              "url": "https://en.wikipedia.org/wiki/Yamaha_YZF-R6"
            },
            "time": 122.617,
            "year": "2025",
            "series": {
              "text": "Supersport",
              "url": "https://en.wikipedia.org/wiki/Sports_motorcycle#Classes"
            }
          },
          {
            "event": {
              "text": "2024 Qatar motorcycle Grand Prix",
              "url": "https://en.wikipedia.org/wiki/2024_Qatar_motorcycle_Grand_Prix"
            },
            "driver": {
              "text": "Tatsuki Suzuki",
              "url": "https://en.wikipedia.org/wiki/Tatsuki_Suzuki"
            },
            "vehicle": {
              "text": "Husqvarna FR250GP",
              "url": "https://en.wikipedia.org/wiki/KTM_RC250GP#Husqvarna_FR250GP"
            },
            "time": 123.135,
            "year": "2024",
            "series": {
              "text": "Moto3",
              "url": "https://en.wikipedia.org/wiki/Grand_Prix_motorcycle_racing#Moto3_class"
            }
          },
          {
            "event": {
              "text": "2026 1st Lusail QSSP 300 round"
            },
            "driver": {
              "text": "Nolann Macary"
            },
            "vehicle": {
              "text": "Kawasaki Ninja 300",
              "url": "https://en.wikipedia.org/wiki/Kawasaki_Ninja_300"
            },
            "time": 136.725,
            "year": "2026",
            "series": {
              "text": "Supersport 300",
              "url": "https://en.wikipedia.org/wiki/Sports_motorcycle#Classes"
            }
          },
          {
            "event": {
              "text": "2024 5th Lusail QTCC round"
            },
            "driver": {
              "text": "Ghanim Al Madheed"
            },
            "vehicle": {
              "text": "Lotus Elise",
              "url": "https://en.wikipedia.org/wiki/Lotus_Elise"
            },
            "time": 139.36,
            "year": "2024",
            "series": {
              "text": "Touring car racing",
              "url": "https://en.wikipedia.org/wiki/Touring_car_racing"
            }
          }
        ]
      },
      {
        "layout": "Short Circuit",
        "years": "2023–present",
        "length_km": 3.701,
        "length_mi": 2.3,
        "turns": 11
      },
      {
        "layout": "Club Circuit",
        "years": "2023–present",
        "length_km": 2.446,
        "length_mi": 1.52,
        "turns": 12
      },
      {
        "layout": "Original Grand Prix Circuit",
        "years": "2004–2022",
        "length_km": 5.38,
        "length_mi": 3.343,
        "turns": 16,
        "race_lap_records": [
          {
            "event": {
              "text": "2021 Qatar Grand Prix",
              "url": "https://en.wikipedia.org/wiki/2021_Qatar_Grand_Prix"
            },
            "driver": {
              "text": "Max Verstappen",
              "url": "https://en.wikipedia.org/wiki/Max_Verstappen"
            },
            "vehicle": {
              "text": "Red Bull Racing RB16B",
              "url": "https://en.wikipedia.org/wiki/Red_Bull_Racing_RB16#2021"
            },
            "time": 83.196,
            "year": "2021",
            "series": {
              "text": "Formula One",
              "url": "https://en.wikipedia.org/wiki/Formula_One"
            }
          },
          {
            "event": {
              "text": "2009 Qatar GP2 Asia Series round",
              "url": "https://en.wikipedia.org/wiki/2009_Qatar_GP2_Asia_Series_round"
            },
            "driver": {
              "text": "Davide Rigon",
              "url": "https://en.wikipedia.org/wiki/Davide_Rigon"
            },
            "vehicle": {
              "text": "Dallara GP2/05",
              "url": "https://en.wikipedia.org/wiki/Dallara_GP2/05"
            },
            "time": 98.699,
            "year": "2009",
            "series": {
              "text": "GP2 Asia",
              "url": "https://en.wikipedia.org/wiki/GP2_Asia_Series"
            }
          },
          {
            "event": {
              "text": "2006 Losail Grand Prix Masters",
              "url": "https://en.wikipedia.org/wiki/Grand_Prix_Masters#2006"
            },
            "driver": {
              "text": "Pierluigi Martini",
              "url": "https://en.wikipedia.org/wiki/Pierluigi_Martini"
            },
            "vehicle": {
              "text": "Delta Motorsport GP Masters car"
            },
            "time": 109.116,
            "year": "2006",
            "series": {
              "text": "GP Masters",
              "url": "https://en.wikipedia.org/wiki/Grand_Prix_Masters"
            }
          },
          {
            "event": {
              "text": "2022 Qatar motorcycle Grand Prix",
              "url": "https://en.wikipedia.org/wiki/2022_Qatar_motorcycle_Grand_Prix"
            },
            "driver": {
              "text": "Enea Bastianini",
              "url": "https://en.wikipedia.org/wiki/Enea_Bastianini"
            },
            "vehicle": {
              "text": "Ducati Desmosedici GP21",
              "url": "https://en.wikipedia.org/wiki/Ducati_Desmosedici"
            },
            "time": 114.338,
            "year": "2022",
            "series": {
              "text": "MotoGP",
              "url": "https://en.wikipedia.org/wiki/Grand_Prix_motorcycle_racing#MotoGP_class"
            }
          },
          {
            "event": {
              "text": "2019 Lusail World SBK round",
              "url": "https://en.wikipedia.org/wiki/2019_Superbike_World_Championship"
            },
            "driver": {
              "text": "Jonathan Rea",
              "url": "https://en.wikipedia.org/wiki/Jonathan_Rea"
            },
            "vehicle": {
              "text": "Kawasaki Ninja ZX-10RR",
              "url": "https://en.wikipedia.org/wiki/Kawasaki_Ninja_ZX-10R"
            },
            "time": 116.687,
            "year": "2019",
            "series": {
              "text": "World SBK",
              "url": "https://en.wikipedia.org/wiki/Superbike_World_Championship"
            }
          },
          {
            "event": {
              "text": "2019 Qatar motorcycle Grand Prix",
              "url": "https://en.wikipedia.org/wiki/2019_Qatar_motorcycle_Grand_Prix"
            },
            "driver": {
              "text": "Thomas Lüthi",
              "url": "https://en.wikipedia.org/wiki/Thomas_L%C3%BCthi"
            },
            "vehicle": {
              "text": "Kalex Moto2",
              "url": "https://en.wikipedia.org/wiki/Kalex"
            },
            "time": 118.711,
            "year": "2019",
            "series": {
              "text": "Moto2",
              "url": "https://en.wikipedia.org/wiki/Grand_Prix_motorcycle_racing#Moto2_class"
            }
          },
          {
            "event": {
              "text": "2008 Qatar motorcycle Grand Prix",
              "url": "https://en.wikipedia.org/wiki/2008_Qatar_motorcycle_Grand_Prix"
            },
            "driver": {
              "text": "Alex Debón",
              "url": "https://en.wikipedia.org/wiki/Alex_Deb%C3%B3n"
            },
            "vehicle": {
              "text": "Aprilia RSV 250",
              "url": "https://en.wikipedia.org/wiki/Aprilia_RSV_250"
            },
            "time": 119.379,
            "year": "2008",
            "series": {
              "text": "250cc",
              "url": "https://en.wikipedia.org/wiki/Grand_Prix_motorcycle_racing#Pre-MotoGP_era"
            }
          },
          {
            "event": {
              "text": "2014 Lusail MRF Challenge round",
              "url": "https://en.wikipedia.org/wiki/2014%E2%80%9315_MRF_Challenge_Formula_2000_Championship"
            },
            "driver": {
              "text": "Toby Sowery",
              "url": "https://en.wikipedia.org/wiki/Toby_Sowery"
            },
            "vehicle": {
              "text": "Dallara Formulino Pro",
              "url": "https://en.wikipedia.org/wiki/List_of_Dallara_cars"
            },
            "time": 119.519,
            "year": "2014",
            "series": {
              "text": "MRF Challenge",
              "url": "https://en.wikipedia.org/wiki/MRF_Challenge"
            }
          },
          {
            "event": {
              "text": "2015 2nd Lusail Porsche GT3 Middle East Championship round",
              "url": "https://en.wikipedia.org/wiki/Porsche_Sprint_Challenge_Middle_East"
            },
            "driver": {
              "text": "Clemens Schmid",
              "url": "https://en.wikipedia.org/wiki/Clemens_Schmid"
            },
            "vehicle": {
              "text": "Porsche 911 (991 I) GT3 Cup",
              "url": "https://en.wikipedia.org/wiki/Porsche_911_GT3#991_GT3_Cup_(2013–2017)"
            },
            "time": 120.322,
            "year": "2015",
            "series": {
              "text": "Porsche Carrera Cup",
              "url": "https://en.wikipedia.org/wiki/Porsche_Carrera_Cup"
            }
          },
          {
            "event": {
              "text": "2015 FIA WTCC Race of Qatar",
              "url": "https://en.wikipedia.org/wiki/2015_World_Touring_Car_Championship"
            },
            "driver": {
              "text": "José María López",
              "url": "https://en.wikipedia.org/wiki/Jos%C3%A9_Mar%C3%ADa_L%C3%B3pez"
            },
            "vehicle": {
              "text": "Citroën C-Elysée WTCC",
              "url": "https://en.wikipedia.org/wiki/Citro%C3%ABn_C-Elys%C3%A9e#Motorsport"
            },
            "time": 121.628,
            "year": "2015",
            "series": {
              "text": "TC1",
              "url": "https://en.wikipedia.org/wiki/Super_2000#Touring_cars"
            }
          },
          {
            "event": {
              "text": "2017 Lusail World SSP round",
              "url": "https://en.wikipedia.org/wiki/2017_Supersport_World_Championship"
            },
            "driver": {
              "text": "Kenan Sofuoğlu",
              "url": "https://en.wikipedia.org/wiki/Kenan_Sofuo%C4%9Flu"
            },
            "vehicle": {
              "text": "Kawasaki Ninja ZX-6R",
              "url": "https://en.wikipedia.org/wiki/Kawasaki_Ninja_ZX-6R"
            },
            "time": 121.832,
            "year": "2017",
            "series": {
              "text": "World SSP",
              "url": "https://en.wikipedia.org/wiki/Supersport_World_Championship"
            }
          },
          {
            "event": {
              "text": "2009 Lusail Speedcar Series round",
              "url": "https://en.wikipedia.org/wiki/2009_Qatar_Speedcar_Series_round"
            },
            "driver": {
              "text": "Vitantonio Liuzzi",
              "url": "https://en.wikipedia.org/wiki/Vitantonio_Liuzzi"
            },
            "vehicle": {
              "text": "Speedcar V8",
              "url": "https://en.wikipedia.org/wiki/Speedcar_Series#Technical_and_sporting_regulations"
            },
            "time": 124.508,
            "year": "2009",
            "series": {
              "text": "Stock car racing",
              "url": "https://en.wikipedia.org/wiki/Stock_car_racing"
            }
          },
          {
            "event": {
              "text": "2019 Qatar motorcycle Grand Prix",
              "url": "https://en.wikipedia.org/wiki/2019_Qatar_motorcycle_Grand_Prix"
            },
            "driver": {
              "text": "Romano Fenati",
              "url": "https://en.wikipedia.org/wiki/Romano_Fenati"
            },
            "vehicle": {
              "text": "Honda NSF250RW",
              "url": "https://en.wikipedia.org/wiki/Honda_NSF250R"
            },
            "time": 125.403,
            "year": "2019",
            "series": {
              "text": "Moto3",
              "url": "https://en.wikipedia.org/wiki/Grand_Prix_motorcycle_racing#Moto3_class"
            }
          },
          {
            "event": {
              "text": "2008 Qatar motorcycle Grand Prix",
              "url": "https://en.wikipedia.org/wiki/2008_Qatar_motorcycle_Grand_Prix"
            },
            "driver": {
              "text": "Scott Redding",
              "url": "https://en.wikipedia.org/wiki/Scott_Redding"
            },
            "vehicle": {
              "text": "Aprilia RS125R",
              "url": "https://en.wikipedia.org/wiki/Aprilia_RS125R"
            },
            "time": 125.695,
            "year": "2008",
            "series": {
              "text": "125cc",
              "url": "https://en.wikipedia.org/wiki/Grand_Prix_motorcycle_racing#Pre-MotoGP_era"
            }
          },
          {
            "event": {
              "text": "2019 Lusail Supersport 300 round",
              "url": "https://en.wikipedia.org/wiki/2019_Supersport_300_World_Championship"
            },
            "driver": {
              "text": "Ana Carrasco",
              "url": "https://en.wikipedia.org/wiki/Ana_Carrasco"
            },
            "vehicle": {
              "text": "Kawasaki Ninja 400",
              "url": "https://en.wikipedia.org/wiki/Kawasaki_Ninja_400"
            },
            "time": 133.798,
            "year": "2019",
            "series": {
              "text": "Supersport 300",
              "url": "https://en.wikipedia.org/wiki/Supersport_300_World_Championship"
            }
          },
          {
            "event": {
              "text": "2015 Lusail ARRC round",
              "url": "https://en.wikipedia.org/wiki/Asia_Road_Racing_Championship"
            },
            "driver": {
              "text": "Kasma Daniel Kasmayudin",
              "url": "https://en.wikipedia.org/wiki/Kasma_Daniel_Kasmayudin"
            },
            "vehicle": {
              "text": "Yamaha YZF-R25",
              "url": "https://en.wikipedia.org/wiki/Yamaha_YZF-R25"
            },
            "time": 144.177,
            "year": "2015",
            "series": {
              "text": "Asia Productions 250",
              "url": "https://en.wikipedia.org/wiki/Asia_Road_Racing_Championship"
            }
          },
          {
            "event": {
              "text": "2014 Lusail ARRC round",
              "url": "https://en.wikipedia.org/wiki/Asia_Road_Racing_Championship"
            },
            "driver": {
              "text": "Ferlando Herdian"
            },
            "vehicle": {
              "text": "Yamaha T-150",
              "url": "https://en.wikipedia.org/wiki/Yamaha_T-150"
            },
            "time": 151.934,
            "year": "2014",
            "series": {
              "text": "Asia Underbone 130",
              "url": "https://en.wikipedia.org/wiki/Asia_Road_Racing_Championship"
            }
          }
        ]
      }
    ]
  }
]